xler8r_lite/__init__.py
xler8r_lite/py.typed
xler8r_lite/_jsii/__init__.py
xler8r_lite/_jsii/xler8r-lite@2.66.11.jsii.tgz
xler8r_lite-2.66.11.dist-info/LICENSE
xler8r_lite-2.66.11.dist-info/METADATA
xler8r_lite-2.66.11.dist-info/WHEEL
xler8r_lite-2.66.11.dist-info/top_level.txt
xler8r_lite-2.66.11.dist-info/RECORD
