Metadata-Version: 2.1
Name: xler8r-lite
Version: 2.66.11
Summary: Fast Track Cloud Adoption with XLER8R Patterns - Lite
Home-page: https://github.com/cre8ivelogix-inc
Author: Muhammad S Tahir <muhammad.tahir@cre8ivelogix.com>
License: MIT-0
Project-URL: Source, https://github.com/cre8ivelogix-inc/xler8r-lite.git
Classifier: Intended Audience :: Developers
Classifier: Operating System :: OS Independent
Classifier: Programming Language :: JavaScript
Classifier: Programming Language :: Python :: 3 :: Only
Classifier: Programming Language :: Python :: 3.7
Classifier: Programming Language :: Python :: 3.8
Classifier: Programming Language :: Python :: 3.9
Classifier: Programming Language :: Python :: 3.10
Classifier: Typing :: Typed
Classifier: License :: OSI Approved
Requires-Python: ~=3.7
License-File: LICENSE
Requires-Dist: aws-cdk-lib (==2.66.1)
Requires-Dist: constructs (<11.0.0,>=10.0.0)
Requires-Dist: jsii (<2.0.0,>=1.75.0)
Requires-Dist: publication (>=0.0.3)
Requires-Dist: typeguard (~=2.13.3)
Requires-Dist: wa-cdk-lite (==2.66.11)
